{
  "login.insertPhoneNumber": "login.insertPhoneNumber",
  "login.loggingIn": "login.loggingIn",
  "login.loginWithEmail": "login.loginWithEmail",
  "login.loginWithPhone": "login.loginWithPhone",
  "login.password": "login.password",
  "login.testLogin": "login.testLogin",
  "navigation.admin": "navigation.admin",
  "navigation.beer": "navigation.beer",
  "navigation.cart": "navigation.cart",
  "navigation.contactUs": "navigation.contactUs",
  "navigation.delivery": "navigation.delivery",
  "navigation.discoverCategories": "navigation.discoverCategories",
  "navigation.home": "navigation.home",
  "navigation.language": "navigation.language",
  "navigation.login": "navigation.login",
  "navigation.logout": "navigation.logout",
  "navigation.menu": "navigation.menu",
  "navigation.needHelp": "navigation.needHelp",
  "navigation.nonAlcoholic": "navigation.nonAlcoholic",
  "navigation.products": "navigation.products",
  "navigation.profile": "navigation.profile",
  "navigation.shop": "navigation.shop",
  "navigation.spirits": "navigation.spirits",
  "navigation.viewAllProducts": "navigation.viewAllProducts",
  "navigation.wine": "navigation.wine",
  "notifications.deliveryMethods": "notifications.deliveryMethods",
  "notifications.emailNotifications": "notifications.emailNotifications",
  "notifications.marketing": "notifications.marketing",
  "notifications.noNotifications": "notifications.noNotifications",
  "notifications.orderUpdates": "notifications.orderUpdates",
  "notifications.pushNotifications": "notifications.pushNotifications",
  "notifications.securityAlerts": "notifications.securityAlerts",
  "notifications.settings": "notifications.settings",
  "notifications.smsNotifications": "notifications.smsNotifications",
  "notifications.systemAlerts": "notifications.systemAlerts",
  "notifications.types": "notifications.types",
  "order.orderNumber": "order.orderNumber",
  "orderDetailPage.backToOrders": "orderDetailPage.backToOrders",
  "orderDetailPage.created": "orderDetailPage.created",
  "orderDetailPage.deliveredAt": "orderDetailPage.deliveredAt",
  "orderDetailPage.deliveryAddress": "orderDetailPage.deliveryAddress",
  "orderDetailPage.deliveryInfo": "orderDetailPage.deliveryInfo",
  "orderDetailPage.deliveryMethod": "orderDetailPage.deliveryMethod",
  "orderDetailPage.deliveryPerson": "orderDetailPage.deliveryPerson",
  "orderDetailPage.each": "orderDetailPage.each",
  "orderDetailPage.estimatedDelivery": "orderDetailPage.estimatedDelivery",
  "orderDetailPage.homeDelivery": "orderDetailPage.homeDelivery",
  "orderDetailPage.notes": "orderDetailPage.notes",
  "orderDetailPage.order": "orderDetailPage.order",
  "orderDetailPage.orderItems": "orderDetailPage.orderItems"
}